remind_me_some/__init__.py
remind_me_some/action.py
remind_me_some/event.py
remind_me_some/goal.py
remind_me_some/is_exclude_date.py
remind_me_some/schedule_actions.py
remind_me_some/schedule_manager.py
remind_me_some-1.0.1.dist-info/LICENSE.txt
remind_me_some-1.0.1.dist-info/METADATA
remind_me_some-1.0.1.dist-info/WHEEL
remind_me_some-1.0.1.dist-info/top_level.txt
remind_me_some-1.0.1.dist-info/RECORD
