Metadata-Version: 2.1
Name: remind-me-some
Version: 1.0.1
Summary: Prioritize your reminders.
Home-page: https://github.com/audrow/remind-me-some
Author: Audrow Nash
Author-email: audrow@hey.com
License: MIT
Keywords: todo list,priorities,productivity
Platform: UNKNOWN
Classifier: Intended Audience :: Developers
Classifier: License :: OSI Approved :: MIT License
Classifier: Programming Language :: Python
Classifier: Programming Language :: Python :: 3
Classifier: Programming Language :: Python :: 3.6
Classifier: Programming Language :: Python :: 3.7
Classifier: Programming Language :: Python :: 3.8
Classifier: Natural Language :: English
Requires-Python: >=3.6
Requires-Dist: flake8
Requires-Dist: freezegun
Requires-Dist: holidays
Requires-Dist: pep257
Requires-Dist: pytest
Requires-Dist: pytest-cov
Requires-Dist: pytest-mock
